MANIFEST.in
README.rst
code-of-conduct.rst
setup.cfg
setup.py
agentzero/__init__.py
agentzero/core.py
agentzero/errors.py
agentzero/serializers.py
agentzero/util.py
agentzero/version.py
agentzero/zero.py
agentzero.egg-info/PKG-INFO
agentzero.egg-info/SOURCES.txt
agentzero.egg-info/dependency_links.txt
agentzero.egg-info/entry_points.txt
agentzero.egg-info/not-zip-safe
agentzero.egg-info/requires.txt
agentzero.egg-info/top_level.txt