Metadata-Version: 1.0
Name: agentzero
Version: 0.4.2
Summary: AgentZero lets you create, connect, bind, and modify zeromq sockets in runtime with ease.
Home-page: https://github.com/gabrielfalcao/agentzero
Author: Gabriel Falcao
Author-email: gabriel@nacaolivre.org
License: UNKNOWN
Platform: UNKNOWN
